Metadata-Version: 2.1
Name: skidtools
Version: 0.0.1a3
Summary: A small utility package to reduce boilerplate code in skid scripts
Home-page: https://docs.clast.dev/skidtools/
Author: Abdos
Author-email: admin.dev@clast.dev
License: UNKNOWN
Platform: UNKNOWN
Classifier: Programming Language :: Python :: 3
Classifier: License :: OSI Approved :: GNU General Public License v3 (GPLv3)
Classifier: Operating System :: OS Independent
Classifier: Development Status :: 3 - Alpha
Classifier: Environment :: Console
Classifier: Topic :: Utilities
Classifier: Typing :: Typed
Requires-Python: >=3.6
